.drone.yml
.gitignore
README.md
setup.cfg
setup.py
django_realtime_admin/__init__.py
django_realtime_admin/admin.py
django_realtime_admin/utils.py
django_realtime_admin.egg-info/PKG-INFO
django_realtime_admin.egg-info/SOURCES.txt
django_realtime_admin.egg-info/dependency_links.txt
django_realtime_admin.egg-info/requires.txt
django_realtime_admin.egg-info/top_level.txt
django_realtime_admin/static/django_realtime_admin/updates.css
django_realtime_admin/static/django_realtime_admin/updates.js
django_realtime_admin/templates/admin/django_realtime_admin/change_list.html
django_realtime_admin/templates/admin/django_realtime_admin/row.html
django_realtime_admin/templatetags/__init__.py
django_realtime_admin/templatetags/django_realtime_admin.py